{"nodes": [{"id": "c_users_dmytro_projects_timeli_sh_apps_admin_package_json", "label": "package.json", "file_type": "code", "source_file": "apps/admin/package.json", "source_location": "L1"}, {"id": "admin_package_name", "label": "name", "file_type": "code", "source_file": "apps/admin/package.json", "source_location": "L2"}, {"id": "admin_package_version", "label": "version", "file_type": "code", "source_file": "apps/admin/package.json", "source_location": "L3"}, {"id": "admin_package_private", "label": "private", "file_type": "code", "source_file": "apps/admin/package.json", "source_location": "L4"}, {"id": "admin_package_scripts", "label": "scripts", "file_type": "code", "source_file": "apps/admin/package.json", "source_location": "L5"}, {"id": "admin_package_scripts_dev", "label": "dev", "file_type": "code", "source_file": "apps/admin/package.json", "source_location": "L6"}, {"id": "admin_package_scripts_generate_font_previews", "label": "generate-font-previews", "file_type": "code", "source_file": "apps/admin/package.json", "source_location": "L7"}, {"id": "admin_package_scripts_purge_organization", "label": "purge-organization", "file_type": "code", "source_file": "apps/admin/package.json", "source_location": "L8"}, {"id": "admin_package_scripts_build", "label": "build", "file_type": "code", "source_file": "apps/admin/package.json", "source_location": "L9"}, {"id": "admin_package_scripts_typegen", "label": "typegen", "file_type": "code", "source_file": "apps/admin/package.json", "source_location": "L10"}, {"id": "admin_package_scripts_start", "label": "start", "file_type": "code", "source_file": "apps/admin/package.json", "source_location": "L11"}, {"id": "admin_package_scripts_lint", "label": "lint", "file_type": "code", "source_file": "apps/admin/package.json", "source_location": "L12"}, {"id": "admin_package_scripts_lint_fix", "label": "lint:fix", "file_type": "code", "source_file": "apps/admin/package.json", "source_location": "L13"}, {"id": "admin_package_dependencies", "label": "dependencies", "file_type": "code", "source_file": "apps/admin/package.json", "source_location": "L15"}, {"id": "admin_package_dependencies_mdx_js_react", "label": "@mdx-js/react", "file_type": "code", "source_file": "apps/admin/package.json", "source_location": "L16"}, {"id": "admin_package_dependencies_polar_sh_better_auth", "label": "@polar-sh/better-auth", "file_type": "code", "source_file": "apps/admin/package.json", "source_location": "L17"}, {"id": "admin_package_dependencies_polar_sh_sdk", "label": "@polar-sh/sdk", "file_type": "code", "source_file": "apps/admin/package.json", "source_location": "L18"}, {"id": "admin_package_dependencies_timelish_api_sdk", "label": "@timelish/api-sdk", "file_type": "code", "source_file": "apps/admin/package.json", "source_location": "L19"}, {"id": "admin_package_dependencies_timelish_app_store", "label": "@timelish/app-store", "file_type": "code", "source_file": "apps/admin/package.json", "source_location": "L20"}, {"id": "admin_package_dependencies_timelish_email_builder", "label": "@timelish/email-builder", "file_type": "code", "source_file": "apps/admin/package.json", "source_location": "L21"}, {"id": "admin_package_dependencies_timelish_i18n", "label": "@timelish/i18n", "file_type": "code", "source_file": "apps/admin/package.json", "source_location": "L22"}, {"id": "admin_package_dependencies_timelish_logger", "label": "@timelish/logger", "file_type": "code", "source_file": "apps/admin/package.json", "source_location": "L23"}, {"id": "admin_package_dependencies_timelish_page_builder", "label": "@timelish/page-builder", "file_type": "code", "source_file": "apps/admin/package.json", "source_location": "L24"}, {"id": "admin_package_dependencies_timelish_rte", "label": "@timelish/rte", "file_type": "code", "source_file": "apps/admin/package.json", "source_location": "L25"}, {"id": "admin_package_dependencies_timelish_services", "label": "@timelish/services", "file_type": "code", "source_file": "apps/admin/package.json", "source_location": "L26"}, {"id": "admin_package_dependencies_timelish_types", "label": "@timelish/types", "file_type": "code", "source_file": "apps/admin/package.json", "source_location": "L27"}, {"id": "admin_package_dependencies_timelish_ui", "label": "@timelish/ui", "file_type": "code", "source_file": "apps/admin/package.json", "source_location": "L28"}, {"id": "admin_package_dependencies_timelish_ui_admin", "label": "@timelish/ui-admin", "file_type": "code", "source_file": "apps/admin/package.json", "source_location": "L29"}, {"id": "admin_package_dependencies_timelish_ui_admin_kit", "label": "@timelish/ui-admin-kit", "file_type": "code", "source_file": "apps/admin/package.json", "source_location": "L30"}, {"id": "admin_package_dependencies_timelish_utils", "label": "@timelish/utils", "file_type": "code", "source_file": "apps/admin/package.json", "source_location": "L31"}, {"id": "admin_package_dependencies_vvo_tzdb", "label": "@vvo/tzdb", "file_type": "code", "source_file": "apps/admin/package.json", "source_location": "L32"}, {"id": "admin_package_dependencies_better_auth", "label": "better-auth", "file_type": "code", "source_file": "apps/admin/package.json", "source_location": "L33"}, {"id": "admin_package_dependencies_class_variance_authority", "label": "class-variance-authority", "file_type": "code", "source_file": "apps/admin/package.json", "source_location": "L34"}, {"id": "admin_package_dependencies_copy_text_to_clipboard", "label": "copy-text-to-clipboard", "file_type": "code", "source_file": "apps/admin/package.json", "source_location": "L35"}, {"id": "admin_package_dependencies_dotenv", "label": "dotenv", "file_type": "code", "source_file": "apps/admin/package.json", "source_location": "L36"}, {"id": "admin_package_dependencies_esbuild", "label": "esbuild", "file_type": "code", "source_file": "apps/admin/package.json", "source_location": "L37"}, {"id": "admin_package_dependencies_i", "label": "i", "file_type": "code", "source_file": "apps/admin/package.json", "source_location": "L38"}, {"id": "admin_package_dependencies_lodash", "label": "lodash", "file_type": "code", "source_file": "apps/admin/package.json", "source_location": "L39"}, {"id": "admin_package_dependencies_lucide_react", "label": "lucide-react", "file_type": "code", "source_file": "apps/admin/package.json", "source_location": "L40"}, {"id": "admin_package_dependencies_luxon", "label": "luxon", "file_type": "code", "source_file": "apps/admin/package.json", "source_location": "L41"}, {"id": "admin_package_dependencies_mdx_bundler", "label": "mdx-bundler", "file_type": "code", "source_file": "apps/admin/package.json", "source_location": "L42"}, {"id": "admin_package_dependencies_mongodb", "label": "mongodb", "file_type": "code", "source_file": "apps/admin/package.json", "source_location": "L43"}, {"id": "admin_package_dependencies_next", "label": "next", "file_type": "code", "source_file": "apps/admin/package.json", "source_location": "L44"}, {"id": "admin_package_dependencies_next_logger", "label": "next-logger", "file_type": "code", "source_file": "apps/admin/package.json", "source_location": "L45"}, {"id": "admin_package_dependencies_next_navigation_guard", "label": "next-navigation-guard", "file_type": "code", "source_file": "apps/admin/package.json", "source_location": "L46"}, {"id": "admin_package_dependencies_nextjs_toploader", "label": "nextjs-toploader", "file_type": "code", "source_file": "apps/admin/package.json", "source_location": "L47"}, {"id": "admin_package_dependencies_npm", "label": "npm", "file_type": "code", "source_file": "apps/admin/package.json", "source_location": "L48"}, {"id": "admin_package_dependencies_p_limit", "label": "p-limit", "file_type": "code", "source_file": "apps/admin/package.json", "source_location": "L49"}, {"id": "admin_package_dependencies_pino_http", "label": "pino-http", "file_type": "code", "source_file": "apps/admin/package.json", "source_location": "L50"}, {"id": "admin_package_dependencies_react", "label": "react", "file_type": "code", "source_file": "apps/admin/package.json", "source_location": "L51"}, {"id": "admin_package_dependencies_react_window", "label": "react-window", "file_type": "code", "source_file": "apps/admin/package.json", "source_location": "L52"}, {"id": "admin_package_dependencies_rehype_pretty_code", "label": "rehype-pretty-code", "file_type": "code", "source_file": "apps/admin/package.json", "source_location": "L53"}, {"id": "admin_package_dependencies_rehype_starry_night", "label": "rehype-starry-night", "file_type": "code", "source_file": "apps/admin/package.json", "source_location": "L54"}, {"id": "admin_package_dependencies_sanitize_filepath", "label": "sanitize-filepath", "file_type": "code", "source_file": "apps/admin/package.json", "source_location": "L55"}, {"id": "admin_package_dependencies_sharp", "label": "sharp", "file_type": "code", "source_file": "apps/admin/package.json", "source_location": "L56"}, {"id": "admin_package_dependencies_shiki", "label": "shiki", "file_type": "code", "source_file": "apps/admin/package.json", "source_location": "L57"}, {"id": "admin_package_devdependencies", "label": "devDependencies", "file_type": "code", "source_file": "apps/admin/package.json", "source_location": "L59"}, {"id": "admin_package_devdependencies_resvg_resvg_js", "label": "@resvg/resvg-js", "file_type": "code", "source_file": "apps/admin/package.json", "source_location": "L60"}, {"id": "admin_package_devdependencies_timelish_eslint_config", "label": "@timelish/eslint-config", "file_type": "code", "source_file": "apps/admin/package.json", "source_location": "L61"}, {"id": "admin_package_devdependencies_timelish_tailwind_config", "label": "@timelish/tailwind-config", "file_type": "code", "source_file": "apps/admin/package.json", "source_location": "L62"}, {"id": "admin_package_devdependencies_timelish_typescript_config", "label": "@timelish/typescript-config", "file_type": "code", "source_file": "apps/admin/package.json", "source_location": "L63"}, {"id": "admin_package_devdependencies_types_color", "label": "@types/color", "file_type": "code", "source_file": "apps/admin/package.json", "source_location": "L64"}, {"id": "admin_package_devdependencies_types_node", "label": "@types/node", "file_type": "code", "source_file": "apps/admin/package.json", "source_location": "L65"}, {"id": "admin_package_devdependencies_types_react", "label": "@types/react", "file_type": "code", "source_file": "apps/admin/package.json", "source_location": "L66"}, {"id": "admin_package_devdependencies_types_react_file_icon", "label": "@types/react-file-icon", "file_type": "code", "source_file": "apps/admin/package.json", "source_location": "L67"}, {"id": "admin_package_devdependencies_postcss", "label": "postcss", "file_type": "code", "source_file": "apps/admin/package.json", "source_location": "L68"}, {"id": "admin_package_devdependencies_raw_loader", "label": "raw-loader", "file_type": "code", "source_file": "apps/admin/package.json", "source_location": "L69"}, {"id": "admin_package_devdependencies_satori", "label": "satori", "file_type": "code", "source_file": "apps/admin/package.json", "source_location": "L70"}, {"id": "admin_package_devdependencies_tailwindcss", "label": "tailwindcss", "file_type": "code", "source_file": "apps/admin/package.json", "source_location": "L71"}, {"id": "admin_package_devdependencies_tailwindcss_animate", "label": "tailwindcss-animate", "file_type": "code", "source_file": "apps/admin/package.json", "source_location": "L72"}, {"id": "admin_package_devdependencies_typescript", "label": "typescript", "file_type": "code", "source_file": "apps/admin/package.json", "source_location": "L73"}, {"id": "admin_package_devdependencies_yaml", "label": "yaml", "file_type": "code", "source_file": "apps/admin/package.json", "source_location": "L74"}, {"id": "admin_package_resolutions", "label": "resolutions", "file_type": "code", "source_file": "apps/admin/package.json", "source_location": "L76"}, {"id": "admin_package_resolutions_types_react", "label": "@types/react", "file_type": "code", "source_file": "apps/admin/package.json", "source_location": "L77"}, {"id": "admin_package_resolutions_types_react_dom", "label": "@types/react-dom", "file_type": "code", "source_file": "apps/admin/package.json", "source_location": "L78"}], "edges": [{"source": "c_users_dmytro_projects_timeli_sh_apps_admin_package_json", "target": "admin_package_name", "relation": "contains", "confidence": "EXTRACTED", "source_file": "apps/admin/package.json", "source_location": "L2", "weight": 1.0}, {"source": "c_users_dmytro_projects_timeli_sh_apps_admin_package_json", "target": "admin_package_version", "relation": "contains", "confidence": "EXTRACTED", "source_file": "apps/admin/package.json", "source_location": "L3", "weight": 1.0}, {"source": "c_users_dmytro_projects_timeli_sh_apps_admin_package_json", "target": "admin_package_private", "relation": "contains", "confidence": "EXTRACTED", "source_file": "apps/admin/package.json", "source_location": "L4", "weight": 1.0}, {"source": "c_users_dmytro_projects_timeli_sh_apps_admin_package_json", "target": "admin_package_scripts", "relation": "contains", "confidence": "EXTRACTED", "source_file": "apps/admin/package.json", "source_location": "L5", "weight": 1.0}, {"source": "admin_package_scripts", "target": "admin_package_scripts_dev", "relation": "contains", "confidence": "EXTRACTED", "source_file": "apps/admin/package.json", "source_location": "L6", "weight": 1.0}, {"source": "admin_package_scripts", "target": "admin_package_scripts_generate_font_previews", "relation": "contains", "confidence": "EXTRACTED", "source_file": "apps/admin/package.json", "source_location": "L7", "weight": 1.0}, {"source": "admin_package_scripts", "target": "admin_package_scripts_purge_organization", "relation": "contains", "confidence": "EXTRACTED", "source_file": "apps/admin/package.json", "source_location": "L8", "weight": 1.0}, {"source": "admin_package_scripts", "target": "admin_package_scripts_build", "relation": "contains", "confidence": "EXTRACTED", "source_file": "apps/admin/package.json", "source_location": "L9", "weight": 1.0}, {"source": "admin_package_scripts", "target": "admin_package_scripts_typegen", "relation": "contains", "confidence": "EXTRACTED", "source_file": "apps/admin/package.json", "source_location": "L10", "weight": 1.0}, {"source": "admin_package_scripts", "target": "admin_package_scripts_start", "relation": "contains", "confidence": "EXTRACTED", "source_file": "apps/admin/package.json", "source_location": "L11", "weight": 1.0}, {"source": "admin_package_scripts", "target": "admin_package_scripts_lint", "relation": "contains", "confidence": "EXTRACTED", "source_file": "apps/admin/package.json", "source_location": "L12", "weight": 1.0}, {"source": "admin_package_scripts", "target": "admin_package_scripts_lint_fix", "relation": "contains", "confidence": "EXTRACTED", "source_file": "apps/admin/package.json", "source_location": "L13", "weight": 1.0}, {"source": "c_users_dmytro_projects_timeli_sh_apps_admin_package_json", "target": "admin_package_dependencies", "relation": "contains", "confidence": "EXTRACTED", "source_file": "apps/admin/package.json", "source_location": "L15", "weight": 1.0}, {"source": "admin_package_dependencies", "target": "admin_package_dependencies_mdx_js_react", "relation": "contains", "confidence": "EXTRACTED", "source_file": "apps/admin/package.json", "source_location": "L16", "weight": 1.0}, {"source": "admin_package_dependencies_mdx_js_react", "target": "mdx_js_react", "relation": "imports", "confidence": "EXTRACTED", "source_file": "apps/admin/package.json", "source_location": "L16", "weight": 1.0, "context": "import"}, {"source": "admin_package_dependencies", "target": "admin_package_dependencies_polar_sh_better_auth", "relation": "contains", "confidence": "EXTRACTED", "source_file": "apps/admin/package.json", "source_location": "L17", "weight": 1.0}, {"source": "admin_package_dependencies_polar_sh_better_auth", "target": "polar_sh_better_auth", "relation": "imports", "confidence": "EXTRACTED", "source_file": "apps/admin/package.json", "source_location": "L17", "weight": 1.0, "context": "import"}, {"source": "admin_package_dependencies", "target": "admin_package_dependencies_polar_sh_sdk", "relation": "contains", "confidence": "EXTRACTED", "source_file": "apps/admin/package.json", "source_location": "L18", "weight": 1.0}, {"source": "admin_package_dependencies_polar_sh_sdk", "target": "polar_sh_sdk", "relation": "imports", "confidence": "EXTRACTED", "source_file": "apps/admin/package.json", "source_location": "L18", "weight": 1.0, "context": "import"}, {"source": "admin_package_dependencies", "target": "admin_package_dependencies_timelish_api_sdk", "relation": "contains", "confidence": "EXTRACTED", "source_file": "apps/admin/package.json", "source_location": "L19", "weight": 1.0}, {"source": "admin_package_dependencies_timelish_api_sdk", "target": "timelish_api_sdk", "relation": "imports", "confidence": "EXTRACTED", "source_file": "apps/admin/package.json", "source_location": "L19", "weight": 1.0, "context": "import"}, {"source": "admin_package_dependencies", "target": "admin_package_dependencies_timelish_app_store", "relation": "contains", "confidence": "EXTRACTED", "source_file": "apps/admin/package.json", "source_location": "L20", "weight": 1.0}, {"source": "admin_package_dependencies_timelish_app_store", "target": "timelish_app_store", "relation": "imports", "confidence": "EXTRACTED", "source_file": "apps/admin/package.json", "source_location": "L20", "weight": 1.0, "context": "import"}, {"source": "admin_package_dependencies", "target": "admin_package_dependencies_timelish_email_builder", "relation": "contains", "confidence": "EXTRACTED", "source_file": "apps/admin/package.json", "source_location": "L21", "weight": 1.0}, {"source": "admin_package_dependencies_timelish_email_builder", "target": "timelish_email_builder", "relation": "imports", "confidence": "EXTRACTED", "source_file": "apps/admin/package.json", "source_location": "L21", "weight": 1.0, "context": "import"}, {"source": "admin_package_dependencies", "target": "admin_package_dependencies_timelish_i18n", "relation": "contains", "confidence": "EXTRACTED", "source_file": "apps/admin/package.json", "source_location": "L22", "weight": 1.0}, {"source": "admin_package_dependencies_timelish_i18n", "target": "timelish_i18n", "relation": "imports", "confidence": "EXTRACTED", "source_file": "apps/admin/package.json", "source_location": "L22", "weight": 1.0, "context": "import"}, {"source": "admin_package_dependencies", "target": "admin_package_dependencies_timelish_logger", "relation": "contains", "confidence": "EXTRACTED", "source_file": "apps/admin/package.json", "source_location": "L23", "weight": 1.0}, {"source": "admin_package_dependencies_timelish_logger", "target": "timelish_logger", "relation": "imports", "confidence": "EXTRACTED", "source_file": "apps/admin/package.json", "source_location": "L23", "weight": 1.0, "context": "import"}, {"source": "admin_package_dependencies", "target": "admin_package_dependencies_timelish_page_builder", "relation": "contains", "confidence": "EXTRACTED", "source_file": "apps/admin/package.json", "source_location": "L24", "weight": 1.0}, {"source": "admin_package_dependencies_timelish_page_builder", "target": "timelish_page_builder", "relation": "imports", "confidence": "EXTRACTED", "source_file": "apps/admin/package.json", "source_location": "L24", "weight": 1.0, "context": "import"}, {"source": "admin_package_dependencies", "target": "admin_package_dependencies_timelish_rte", "relation": "contains", "confidence": "EXTRACTED", "source_file": "apps/admin/package.json", "source_location": "L25", "weight": 1.0}, {"source": "admin_package_dependencies_timelish_rte", "target": "timelish_rte", "relation": "imports", "confidence": "EXTRACTED", "source_file": "apps/admin/package.json", "source_location": "L25", "weight": 1.0, "context": "import"}, {"source": "admin_package_dependencies", "target": "admin_package_dependencies_timelish_services", "relation": "contains", "confidence": "EXTRACTED", "source_file": "apps/admin/package.json", "source_location": "L26", "weight": 1.0}, {"source": "admin_package_dependencies_timelish_services", "target": "timelish_services", "relation": "imports", "confidence": "EXTRACTED", "source_file": "apps/admin/package.json", "source_location": "L26", "weight": 1.0, "context": "import"}, {"source": "admin_package_dependencies", "target": "admin_package_dependencies_timelish_types", "relation": "contains", "confidence": "EXTRACTED", "source_file": "apps/admin/package.json", "source_location": "L27", "weight": 1.0}, {"source": "admin_package_dependencies_timelish_types", "target": "timelish_types", "relation": "imports", "confidence": "EXTRACTED", "source_file": "apps/admin/package.json", "source_location": "L27", "weight": 1.0, "context": "import"}, {"source": "admin_package_dependencies", "target": "admin_package_dependencies_timelish_ui", "relation": "contains", "confidence": "EXTRACTED", "source_file": "apps/admin/package.json", "source_location": "L28", "weight": 1.0}, {"source": "admin_package_dependencies_timelish_ui", "target": "timelish_ui", "relation": "imports", "confidence": "EXTRACTED", "source_file": "apps/admin/package.json", "source_location": "L28", "weight": 1.0, "context": "import"}, {"source": "admin_package_dependencies", "target": "admin_package_dependencies_timelish_ui_admin", "relation": "contains", "confidence": "EXTRACTED", "source_file": "apps/admin/package.json", "source_location": "L29", "weight": 1.0}, {"source": "admin_package_dependencies_timelish_ui_admin", "target": "timelish_ui_admin", "relation": "imports", "confidence": "EXTRACTED", "source_file": "apps/admin/package.json", "source_location": "L29", "weight": 1.0, "context": "import"}, {"source": "admin_package_dependencies", "target": "admin_package_dependencies_timelish_ui_admin_kit", "relation": "contains", "confidence": "EXTRACTED", "source_file": "apps/admin/package.json", "source_location": "L30", "weight": 1.0}, {"source": "admin_package_dependencies_timelish_ui_admin_kit", "target": "timelish_ui_admin_kit", "relation": "imports", "confidence": "EXTRACTED", "source_file": "apps/admin/package.json", "source_location": "L30", "weight": 1.0, "context": "import"}, {"source": "admin_package_dependencies", "target": "admin_package_dependencies_timelish_utils", "relation": "contains", "confidence": "EXTRACTED", "source_file": "apps/admin/package.json", "source_location": "L31", "weight": 1.0}, {"source": "admin_package_dependencies_timelish_utils", "target": "timelish_utils", "relation": "imports", "confidence": "EXTRACTED", "source_file": "apps/admin/package.json", "source_location": "L31", "weight": 1.0, "context": "import"}, {"source": "admin_package_dependencies", "target": "admin_package_dependencies_vvo_tzdb", "relation": "contains", "confidence": "EXTRACTED", "source_file": "apps/admin/package.json", "source_location": "L32", "weight": 1.0}, {"source": "admin_package_dependencies_vvo_tzdb", "target": "vvo_tzdb", "relation": "imports", "confidence": "EXTRACTED", "source_file": "apps/admin/package.json", "source_location": "L32", "weight": 1.0, "context": "import"}, {"source": "admin_package_dependencies", "target": "admin_package_dependencies_better_auth", "relation": "contains", "confidence": "EXTRACTED", "source_file": "apps/admin/package.json", "source_location": "L33", "weight": 1.0}, {"source": "admin_package_dependencies_better_auth", "target": "better_auth", "relation": "imports", "confidence": "EXTRACTED", "source_file": "apps/admin/package.json", "source_location": "L33", "weight": 1.0, "context": "import"}, {"source": "admin_package_dependencies", "target": "admin_package_dependencies_class_variance_authority", "relation": "contains", "confidence": "EXTRACTED", "source_file": "apps/admin/package.json", "source_location": "L34", "weight": 1.0}, {"source": "admin_package_dependencies_class_variance_authority", "target": "class_variance_authority", "relation": "imports", "confidence": "EXTRACTED", "source_file": "apps/admin/package.json", "source_location": "L34", "weight": 1.0, "context": "import"}, {"source": "admin_package_dependencies", "target": "admin_package_dependencies_copy_text_to_clipboard", "relation": "contains", "confidence": "EXTRACTED", "source_file": "apps/admin/package.json", "source_location": "L35", "weight": 1.0}, {"source": "admin_package_dependencies_copy_text_to_clipboard", "target": "copy_text_to_clipboard", "relation": "imports", "confidence": "EXTRACTED", "source_file": "apps/admin/package.json", "source_location": "L35", "weight": 1.0, "context": "import"}, {"source": "admin_package_dependencies", "target": "admin_package_dependencies_dotenv", "relation": "contains", "confidence": "EXTRACTED", "source_file": "apps/admin/package.json", "source_location": "L36", "weight": 1.0}, {"source": "admin_package_dependencies_dotenv", "target": "dotenv", "relation": "imports", "confidence": "EXTRACTED", "source_file": "apps/admin/package.json", "source_location": "L36", "weight": 1.0, "context": "import"}, {"source": "admin_package_dependencies", "target": "admin_package_dependencies_esbuild", "relation": "contains", "confidence": "EXTRACTED", "source_file": "apps/admin/package.json", "source_location": "L37", "weight": 1.0}, {"source": "admin_package_dependencies_esbuild", "target": "esbuild", "relation": "imports", "confidence": "EXTRACTED", "source_file": "apps/admin/package.json", "source_location": "L37", "weight": 1.0, "context": "import"}, {"source": "admin_package_dependencies", "target": "admin_package_dependencies_i", "relation": "contains", "confidence": "EXTRACTED", "source_file": "apps/admin/package.json", "source_location": "L38", "weight": 1.0}, {"source": "admin_package_dependencies_i", "target": "i", "relation": "imports", "confidence": "EXTRACTED", "source_file": "apps/admin/package.json", "source_location": "L38", "weight": 1.0, "context": "import"}, {"source": "admin_package_dependencies", "target": "admin_package_dependencies_lodash", "relation": "contains", "confidence": "EXTRACTED", "source_file": "apps/admin/package.json", "source_location": "L39", "weight": 1.0}, {"source": "admin_package_dependencies_lodash", "target": "lodash", "relation": "imports", "confidence": "EXTRACTED", "source_file": "apps/admin/package.json", "source_location": "L39", "weight": 1.0, "context": "import"}, {"source": "admin_package_dependencies", "target": "admin_package_dependencies_lucide_react", "relation": "contains", "confidence": "EXTRACTED", "source_file": "apps/admin/package.json", "source_location": "L40", "weight": 1.0}, {"source": "admin_package_dependencies_lucide_react", "target": "lucide_react", "relation": "imports", "confidence": "EXTRACTED", "source_file": "apps/admin/package.json", "source_location": "L40", "weight": 1.0, "context": "import"}, {"source": "admin_package_dependencies", "target": "admin_package_dependencies_luxon", "relation": "contains", "confidence": "EXTRACTED", "source_file": "apps/admin/package.json", "source_location": "L41", "weight": 1.0}, {"source": "admin_package_dependencies_luxon", "target": "luxon", "relation": "imports", "confidence": "EXTRACTED", "source_file": "apps/admin/package.json", "source_location": "L41", "weight": 1.0, "context": "import"}, {"source": "admin_package_dependencies", "target": "admin_package_dependencies_mdx_bundler", "relation": "contains", "confidence": "EXTRACTED", "source_file": "apps/admin/package.json", "source_location": "L42", "weight": 1.0}, {"source": "admin_package_dependencies_mdx_bundler", "target": "mdx_bundler", "relation": "imports", "confidence": "EXTRACTED", "source_file": "apps/admin/package.json", "source_location": "L42", "weight": 1.0, "context": "import"}, {"source": "admin_package_dependencies", "target": "admin_package_dependencies_mongodb", "relation": "contains", "confidence": "EXTRACTED", "source_file": "apps/admin/package.json", "source_location": "L43", "weight": 1.0}, {"source": "admin_package_dependencies_mongodb", "target": "mongodb", "relation": "imports", "confidence": "EXTRACTED", "source_file": "apps/admin/package.json", "source_location": "L43", "weight": 1.0, "context": "import"}, {"source": "admin_package_dependencies", "target": "admin_package_dependencies_next", "relation": "contains", "confidence": "EXTRACTED", "source_file": "apps/admin/package.json", "source_location": "L44", "weight": 1.0}, {"source": "admin_package_dependencies_next", "target": "next", "relation": "imports", "confidence": "EXTRACTED", "source_file": "apps/admin/package.json", "source_location": "L44", "weight": 1.0, "context": "import"}, {"source": "admin_package_dependencies", "target": "admin_package_dependencies_next_logger", "relation": "contains", "confidence": "EXTRACTED", "source_file": "apps/admin/package.json", "source_location": "L45", "weight": 1.0}, {"source": "admin_package_dependencies_next_logger", "target": "next_logger", "relation": "imports", "confidence": "EXTRACTED", "source_file": "apps/admin/package.json", "source_location": "L45", "weight": 1.0, "context": "import"}, {"source": "admin_package_dependencies", "target": "admin_package_dependencies_next_navigation_guard", "relation": "contains", "confidence": "EXTRACTED", "source_file": "apps/admin/package.json", "source_location": "L46", "weight": 1.0}, {"source": "admin_package_dependencies_next_navigation_guard", "target": "next_navigation_guard", "relation": "imports", "confidence": "EXTRACTED", "source_file": "apps/admin/package.json", "source_location": "L46", "weight": 1.0, "context": "import"}, {"source": "admin_package_dependencies", "target": "admin_package_dependencies_nextjs_toploader", "relation": "contains", "confidence": "EXTRACTED", "source_file": "apps/admin/package.json", "source_location": "L47", "weight": 1.0}, {"source": "admin_package_dependencies_nextjs_toploader", "target": "nextjs_toploader", "relation": "imports", "confidence": "EXTRACTED", "source_file": "apps/admin/package.json", "source_location": "L47", "weight": 1.0, "context": "import"}, {"source": "admin_package_dependencies", "target": "admin_package_dependencies_npm", "relation": "contains", "confidence": "EXTRACTED", "source_file": "apps/admin/package.json", "source_location": "L48", "weight": 1.0}, {"source": "admin_package_dependencies_npm", "target": "npm", "relation": "imports", "confidence": "EXTRACTED", "source_file": "apps/admin/package.json", "source_location": "L48", "weight": 1.0, "context": "import"}, {"source": "admin_package_dependencies", "target": "admin_package_dependencies_p_limit", "relation": "contains", "confidence": "EXTRACTED", "source_file": "apps/admin/package.json", "source_location": "L49", "weight": 1.0}, {"source": "admin_package_dependencies_p_limit", "target": "p_limit", "relation": "imports", "confidence": "EXTRACTED", "source_file": "apps/admin/package.json", "source_location": "L49", "weight": 1.0, "context": "import"}, {"source": "admin_package_dependencies", "target": "admin_package_dependencies_pino_http", "relation": "contains", "confidence": "EXTRACTED", "source_file": "apps/admin/package.json", "source_location": "L50", "weight": 1.0}, {"source": "admin_package_dependencies_pino_http", "target": "pino_http", "relation": "imports", "confidence": "EXTRACTED", "source_file": "apps/admin/package.json", "source_location": "L50", "weight": 1.0, "context": "import"}, {"source": "admin_package_dependencies", "target": "admin_package_dependencies_react", "relation": "contains", "confidence": "EXTRACTED", "source_file": "apps/admin/package.json", "source_location": "L51", "weight": 1.0}, {"source": "admin_package_dependencies_react", "target": "react", "relation": "imports", "confidence": "EXTRACTED", "source_file": "apps/admin/package.json", "source_location": "L51", "weight": 1.0, "context": "import"}, {"source": "admin_package_dependencies", "target": "admin_package_dependencies_react_window", "relation": "contains", "confidence": "EXTRACTED", "source_file": "apps/admin/package.json", "source_location": "L52", "weight": 1.0}, {"source": "admin_package_dependencies_react_window", "target": "react_window", "relation": "imports", "confidence": "EXTRACTED", "source_file": "apps/admin/package.json", "source_location": "L52", "weight": 1.0, "context": "import"}, {"source": "admin_package_dependencies", "target": "admin_package_dependencies_rehype_pretty_code", "relation": "contains", "confidence": "EXTRACTED", "source_file": "apps/admin/package.json", "source_location": "L53", "weight": 1.0}, {"source": "admin_package_dependencies_rehype_pretty_code", "target": "rehype_pretty_code", "relation": "imports", "confidence": "EXTRACTED", "source_file": "apps/admin/package.json", "source_location": "L53", "weight": 1.0, "context": "import"}, {"source": "admin_package_dependencies", "target": "admin_package_dependencies_rehype_starry_night", "relation": "contains", "confidence": "EXTRACTED", "source_file": "apps/admin/package.json", "source_location": "L54", "weight": 1.0}, {"source": "admin_package_dependencies_rehype_starry_night", "target": "rehype_starry_night", "relation": "imports", "confidence": "EXTRACTED", "source_file": "apps/admin/package.json", "source_location": "L54", "weight": 1.0, "context": "import"}, {"source": "admin_package_dependencies", "target": "admin_package_dependencies_sanitize_filepath", "relation": "contains", "confidence": "EXTRACTED", "source_file": "apps/admin/package.json", "source_location": "L55", "weight": 1.0}, {"source": "admin_package_dependencies_sanitize_filepath", "target": "sanitize_filepath", "relation": "imports", "confidence": "EXTRACTED", "source_file": "apps/admin/package.json", "source_location": "L55", "weight": 1.0, "context": "import"}, {"source": "admin_package_dependencies", "target": "admin_package_dependencies_sharp", "relation": "contains", "confidence": "EXTRACTED", "source_file": "apps/admin/package.json", "source_location": "L56", "weight": 1.0}, {"source": "admin_package_dependencies_sharp", "target": "sharp", "relation": "imports", "confidence": "EXTRACTED", "source_file": "apps/admin/package.json", "source_location": "L56", "weight": 1.0, "context": "import"}, {"source": "admin_package_dependencies", "target": "admin_package_dependencies_shiki", "relation": "contains", "confidence": "EXTRACTED", "source_file": "apps/admin/package.json", "source_location": "L57", "weight": 1.0}, {"source": "admin_package_dependencies_shiki", "target": "shiki", "relation": "imports", "confidence": "EXTRACTED", "source_file": "apps/admin/package.json", "source_location": "L57", "weight": 1.0, "context": "import"}, {"source": "c_users_dmytro_projects_timeli_sh_apps_admin_package_json", "target": "admin_package_devdependencies", "relation": "contains", "confidence": "EXTRACTED", "source_file": "apps/admin/package.json", "source_location": "L59", "weight": 1.0}, {"source": "admin_package_devdependencies", "target": "admin_package_devdependencies_resvg_resvg_js", "relation": "contains", "confidence": "EXTRACTED", "source_file": "apps/admin/package.json", "source_location": "L60", "weight": 1.0}, {"source": "admin_package_devdependencies_resvg_resvg_js", "target": "resvg_resvg_js", "relation": "imports", "confidence": "EXTRACTED", "source_file": "apps/admin/package.json", "source_location": "L60", "weight": 1.0, "context": "import"}, {"source": "admin_package_devdependencies", "target": "admin_package_devdependencies_timelish_eslint_config", "relation": "contains", "confidence": "EXTRACTED", "source_file": "apps/admin/package.json", "source_location": "L61", "weight": 1.0}, {"source": "admin_package_devdependencies_timelish_eslint_config", "target": "timelish_eslint_config", "relation": "imports", "confidence": "EXTRACTED", "source_file": "apps/admin/package.json", "source_location": "L61", "weight": 1.0, "context": "import"}, {"source": "admin_package_devdependencies", "target": "admin_package_devdependencies_timelish_tailwind_config", "relation": "contains", "confidence": "EXTRACTED", "source_file": "apps/admin/package.json", "source_location": "L62", "weight": 1.0}, {"source": "admin_package_devdependencies_timelish_tailwind_config", "target": "timelish_tailwind_config", "relation": "imports", "confidence": "EXTRACTED", "source_file": "apps/admin/package.json", "source_location": "L62", "weight": 1.0, "context": "import"}, {"source": "admin_package_devdependencies", "target": "admin_package_devdependencies_timelish_typescript_config", "relation": "contains", "confidence": "EXTRACTED", "source_file": "apps/admin/package.json", "source_location": "L63", "weight": 1.0}, {"source": "admin_package_devdependencies_timelish_typescript_config", "target": "timelish_typescript_config", "relation": "imports", "confidence": "EXTRACTED", "source_file": "apps/admin/package.json", "source_location": "L63", "weight": 1.0, "context": "import"}, {"source": "admin_package_devdependencies", "target": "admin_package_devdependencies_types_color", "relation": "contains", "confidence": "EXTRACTED", "source_file": "apps/admin/package.json", "source_location": "L64", "weight": 1.0}, {"source": "admin_package_devdependencies_types_color", "target": "types_color", "relation": "imports", "confidence": "EXTRACTED", "source_file": "apps/admin/package.json", "source_location": "L64", "weight": 1.0, "context": "import"}, {"source": "admin_package_devdependencies", "target": "admin_package_devdependencies_types_node", "relation": "contains", "confidence": "EXTRACTED", "source_file": "apps/admin/package.json", "source_location": "L65", "weight": 1.0}, {"source": "admin_package_devdependencies_types_node", "target": "types_node", "relation": "imports", "confidence": "EXTRACTED", "source_file": "apps/admin/package.json", "source_location": "L65", "weight": 1.0, "context": "import"}, {"source": "admin_package_devdependencies", "target": "admin_package_devdependencies_types_react", "relation": "contains", "confidence": "EXTRACTED", "source_file": "apps/admin/package.json", "source_location": "L66", "weight": 1.0}, {"source": "admin_package_devdependencies_types_react", "target": "types_react", "relation": "imports", "confidence": "EXTRACTED", "source_file": "apps/admin/package.json", "source_location": "L66", "weight": 1.0, "context": "import"}, {"source": "admin_package_devdependencies", "target": "admin_package_devdependencies_types_react_file_icon", "relation": "contains", "confidence": "EXTRACTED", "source_file": "apps/admin/package.json", "source_location": "L67", "weight": 1.0}, {"source": "admin_package_devdependencies_types_react_file_icon", "target": "types_react_file_icon", "relation": "imports", "confidence": "EXTRACTED", "source_file": "apps/admin/package.json", "source_location": "L67", "weight": 1.0, "context": "import"}, {"source": "admin_package_devdependencies", "target": "admin_package_devdependencies_postcss", "relation": "contains", "confidence": "EXTRACTED", "source_file": "apps/admin/package.json", "source_location": "L68", "weight": 1.0}, {"source": "admin_package_devdependencies_postcss", "target": "postcss", "relation": "imports", "confidence": "EXTRACTED", "source_file": "apps/admin/package.json", "source_location": "L68", "weight": 1.0, "context": "import"}, {"source": "admin_package_devdependencies", "target": "admin_package_devdependencies_raw_loader", "relation": "contains", "confidence": "EXTRACTED", "source_file": "apps/admin/package.json", "source_location": "L69", "weight": 1.0}, {"source": "admin_package_devdependencies_raw_loader", "target": "raw_loader", "relation": "imports", "confidence": "EXTRACTED", "source_file": "apps/admin/package.json", "source_location": "L69", "weight": 1.0, "context": "import"}, {"source": "admin_package_devdependencies", "target": "admin_package_devdependencies_satori", "relation": "contains", "confidence": "EXTRACTED", "source_file": "apps/admin/package.json", "source_location": "L70", "weight": 1.0}, {"source": "admin_package_devdependencies_satori", "target": "satori", "relation": "imports", "confidence": "EXTRACTED", "source_file": "apps/admin/package.json", "source_location": "L70", "weight": 1.0, "context": "import"}, {"source": "admin_package_devdependencies", "target": "admin_package_devdependencies_tailwindcss", "relation": "contains", "confidence": "EXTRACTED", "source_file": "apps/admin/package.json", "source_location": "L71", "weight": 1.0}, {"source": "admin_package_devdependencies_tailwindcss", "target": "tailwindcss", "relation": "imports", "confidence": "EXTRACTED", "source_file": "apps/admin/package.json", "source_location": "L71", "weight": 1.0, "context": "import"}, {"source": "admin_package_devdependencies", "target": "admin_package_devdependencies_tailwindcss_animate", "relation": "contains", "confidence": "EXTRACTED", "source_file": "apps/admin/package.json", "source_location": "L72", "weight": 1.0}, {"source": "admin_package_devdependencies_tailwindcss_animate", "target": "tailwindcss_animate", "relation": "imports", "confidence": "EXTRACTED", "source_file": "apps/admin/package.json", "source_location": "L72", "weight": 1.0, "context": "import"}, {"source": "admin_package_devdependencies", "target": "admin_package_devdependencies_typescript", "relation": "contains", "confidence": "EXTRACTED", "source_file": "apps/admin/package.json", "source_location": "L73", "weight": 1.0}, {"source": "admin_package_devdependencies_typescript", "target": "typescript", "relation": "imports", "confidence": "EXTRACTED", "source_file": "apps/admin/package.json", "source_location": "L73", "weight": 1.0, "context": "import"}, {"source": "admin_package_devdependencies", "target": "admin_package_devdependencies_yaml", "relation": "contains", "confidence": "EXTRACTED", "source_file": "apps/admin/package.json", "source_location": "L74", "weight": 1.0}, {"source": "admin_package_devdependencies_yaml", "target": "yaml", "relation": "imports", "confidence": "EXTRACTED", "source_file": "apps/admin/package.json", "source_location": "L74", "weight": 1.0, "context": "import"}, {"source": "c_users_dmytro_projects_timeli_sh_apps_admin_package_json", "target": "admin_package_resolutions", "relation": "contains", "confidence": "EXTRACTED", "source_file": "apps/admin/package.json", "source_location": "L76", "weight": 1.0}, {"source": "admin_package_resolutions", "target": "admin_package_resolutions_types_react", "relation": "contains", "confidence": "EXTRACTED", "source_file": "apps/admin/package.json", "source_location": "L77", "weight": 1.0}, {"source": "admin_package_resolutions", "target": "admin_package_resolutions_types_react_dom", "relation": "contains", "confidence": "EXTRACTED", "source_file": "apps/admin/package.json", "source_location": "L78", "weight": 1.0}]}